LICENSE.txt
MANIFEST.in
README.md
setup.py
ut2d/__init__.py
ut2d/main.py
ut2d.egg-info/PKG-INFO
ut2d.egg-info/SOURCES.txt
ut2d.egg-info/dependency_links.txt
ut2d.egg-info/entry_points.txt
ut2d.egg-info/requires.txt
ut2d.egg-info/top_level.txt
ut2d.egg-info/zip-safe
ut2d/lib/__init__.py
ut2d/lib/emoji.py
ut2d/lib/message.py
ut2d/lib/time.py
ut2d/lib/timezone_scrapper.py