Metadata-Version: 2.1
Name: ut2d
Version: 0.3.1
Summary: a command-line utility to convert unitx timestamp into human readable datetime
Home-page: https://github.com/estepona/ut2d
Author: Binghuan Zhang
Author-email: 574953550@qq.com
License: UNKNOWN
Keywords: timestamp datetime command-line scrap
Platform: UNKNOWN
Classifier: Development Status :: 3 - Alpha
Classifier: Environment :: Console
Classifier: Intended Audience :: Developers
Classifier: License :: OSI Approved :: MIT License
Classifier: Natural Language :: English
Classifier: Operating System :: OS Independent
Classifier: Programming Language :: Python :: 3.6
Classifier: Programming Language :: Python :: 3.7
Classifier: Programming Language :: Python :: 3.8
Classifier: Topic :: Internet
Classifier: Topic :: Internet :: WWW/HTTP
Classifier: Topic :: Utilities
